gampixpy/__init__.py
gampixpy/config.py
gampixpy/coordinates.py
gampixpy/detector.py
gampixpy/generator.py
gampixpy/input_parsing.py
gampixpy/mobility.py
gampixpy/output.py
gampixpy/plotting.py
gampixpy/readout_objects.py
gampixpy/recombination.py
gampixpy/tracks.py
gampixpy/units.py
gampixpy/detector_config/coh_250.yaml
gampixpy/detector_config/default.yaml
gampixpy/detector_config/far_detector.yaml
gampixpy/physics_config/default.yaml
gampixpy/readout_config/GAMPixD.yaml
gampixpy/readout_config/GAMPixD_notruth.yaml
gampixpy/readout_config/GAMPixD_vertex_tagging.yaml
gampixpy/readout_config/default.yaml
gampixpy/readout_config/demo_large_pixels.yaml
gampixpy/readout_config/far_detector.yaml
gampixpy/readout_config/larpix.yaml
gampixpy-0.2.1.dist-info/licenses/LICENSE
gampixpy-0.2.1.dist-info/METADATA
gampixpy-0.2.1.dist-info/WHEEL
gampixpy-0.2.1.dist-info/dependency_links.txt
gampixpy-0.2.1.dist-info/top_level.txt
gampixpy-0.2.1.dist-info/RECORD
