Metadata-Version: 2.4
Name: gampixpy
Version: 0.2.1
Summary: Gampix Readout Simulation
Home-page: https://github.com/DanielMDouglas/GAMPixPy
Author: SLAC National Accelerator Laboratory
Author-email: dougl215@slac.stanford.edu
Classifier: Development Status :: 4 - Beta
Classifier: Intended Audience :: Science/Research
Classifier: License :: OSI Approved :: MIT License
Classifier: Operating System :: OS Independent
Classifier: Programming Language :: Python :: 3
Classifier: Topic :: Scientific/Engineering :: Physics
Requires-Python: >=3.2
License-File: LICENSE
Requires-Dist: numpy
Requires-Dist: h5py
Requires-Dist: tqdm
Requires-Dist: torchist
Requires-Dist: particle
Requires-Dist: pyyaml
Dynamic: author
Dynamic: author-email
Dynamic: classifier
Dynamic: home-page
Dynamic: license-file
Dynamic: requires-dist
Dynamic: requires-python
Dynamic: summary
